[
  {
    "region": "francecentral",
    "sku": "Standard_NC6s_v3",
    "gpu_name": "Tesla V100 (16GB)",
    "gpu_count": 1,
    "vcpus": 6,
    "ram_gb": 112,
    "spot_price_usd_hr": 0.6616,
    "ondemand_price_usd_hr": 3.58,
    "savings_pct": 81.5,
    "availability": "high"
  },
  {
    "region": "francecentral",
    "sku": "Standard_NC12s_v3",
    "gpu_name": "Tesla V100 (16GB)",
    "gpu_count": 2,
    "vcpus": 12,
    "ram_gb": 224,
    "spot_price_usd_hr": 1.3232,
    "ondemand_price_usd_hr": 7.16,
    "savings_pct": 81.5,
    "availability": "high"
  },
  {
    "region": "francecentral",
    "sku": "Standard_NC24rs_v3",
    "gpu_name": "Tesla V100 (16GB)",
    "gpu_count": 4,
    "vcpus": 24,
    "ram_gb": 448,
    "spot_price_usd_hr": 2.9112,
    "ondemand_price_usd_hr": 15.408,
    "savings_pct": 81.1,
    "availability": "medium"
  },
  {
    "region": "francecentral",
    "sku": "Standard_NC48ads_A100_v4",
    "gpu_name": "A100 (80GB)",
    "gpu_count": 2,
    "vcpus": 48,
    "ram_gb": 440,
    "spot_price_usd_hr": 1.697,
    "ondemand_price_usd_hr": 8.496,
    "savings_pct": 80.0,
    "availability": "low"
  },
  {
    "region": "francecentral",
    "sku": "Standard_NC96ads_A100_v4",
    "gpu_name": "A100 (80GB)",
    "gpu_count": 4,
    "vcpus": 96,
    "ram_gb": 880,
    "spot_price_usd_hr": 3.3939,
    "ondemand_price_usd_hr": 16.992,
    "savings_pct": 80.0,
    "availability": "low"
  },
  {
    "region": "francecentral",
    "sku": "Standard_NC64as_T4_v3",
    "gpu_name": "Tesla T4 (16GB)",
    "gpu_count": 4,
    "vcpus": 64,
    "ram_gb": 440,
    "spot_price_usd_hr": 1.4723,
    "ondemand_price_usd_hr": 5.824,
    "savings_pct": 74.7,
    "availability": "high"
  },
  {
    "region": "francecentral",
    "sku": "Standard_NV6ads_A10_v5",
    "gpu_name": "A10 (6GB slice)",
    "gpu_count": 1,
    "vcpus": 6,
    "ram_gb": 55,
    "spot_price_usd_hr": 0.1048,
    "ondemand_price_usd_hr": 0.55,
    "savings_pct": 80.9,
    "availability": "high"
  },
  {
    "region": "westeurope",
    "sku": "Standard_NC24s_v3",
    "gpu_name": "Tesla V100 (16GB)",
    "gpu_count": 4,
    "vcpus": 24,
    "ram_gb": 448,
    "spot_price_usd_hr": 2.826,
    "ondemand_price_usd_hr": 14.688,
    "savings_pct": 80.8,
    "availability": "medium"
  },
  {
    "region": "westeurope",
    "sku": "Standard_NCC40ads_H100_v5",
    "gpu_name": "H100 (80GB)",
    "gpu_count": 1,
    "vcpus": 40,
    "ram_gb": 320,
    "spot_price_usd_hr": 1.6447,
    "ondemand_price_usd_hr": 10.32,
    "savings_pct": 84.1,
    "availability": "low"
  },
  {
    "region": "westeurope",
    "sku": "Standard_NC48ads_A100_v4",
    "gpu_name": "A100 (80GB)",
    "gpu_count": 2,
    "vcpus": 48,
    "ram_gb": 440,
    "spot_price_usd_hr": 4.8399,
    "ondemand_price_usd_hr": 16.128,
    "savings_pct": 70.0,
    "availability": "low"
  },
  {
    "region": "westeurope",
    "sku": "Standard_NC32ads_A10_v4",
    "gpu_name": "A10 (24GB)",
    "gpu_count": 2,
    "vcpus": 32,
    "ram_gb": 220,
    "spot_price_usd_hr": 1.0571,
    "ondemand_price_usd_hr": 4.752,
    "savings_pct": 77.8,
    "availability": "medium"
  },
  {
    "region": "westeurope",
    "sku": "Standard_NC16as_T4_v3",
    "gpu_name": "Tesla T4 (16GB)",
    "gpu_count": 1,
    "vcpus": 16,
    "ram_gb": 110,
    "spot_price_usd_hr": 0.8116,
    "ondemand_price_usd_hr": 2.912,
    "savings_pct": 72.1,
    "availability": "high"
  },
  {
    "region": "westeurope",
    "sku": "Standard_NC8ads_A10_v4",
    "gpu_name": "A10 (24GB)",
    "gpu_count": 1,
    "vcpus": 8,
    "ram_gb": 55,
    "spot_price_usd_hr": 0.3323,
    "ondemand_price_usd_hr": 1.188,
    "savings_pct": 72.0,
    "availability": "high"
  },
  {
    "region": "uksouth",
    "sku": "Standard_NC4as_T4_v3",
    "gpu_name": "Tesla T4 (16GB)",
    "gpu_count": 1,
    "vcpus": 4,
    "ram_gb": 28,
    "spot_price_usd_hr": 0.364,
    "ondemand_price_usd_hr": 1.456,
    "savings_pct": 75.0,
    "availability": "high"
  },
  {
    "region": "uksouth",
    "sku": "Standard_NC6s_v3",
    "gpu_name": "Tesla V100 (16GB)",
    "gpu_count": 1,
    "vcpus": 6,
    "ram_gb": 112,
    "spot_price_usd_hr": 0.6632,
    "ondemand_price_usd_hr": 3.856,
    "savings_pct": 82.8,
    "availability": "medium"
  },
  {
    "region": "uksouth",
    "sku": "Standard_NC64as_T4_v3",
    "gpu_name": "Tesla T4 (16GB)",
    "gpu_count": 4,
    "vcpus": 64,
    "ram_gb": 440,
    "spot_price_usd_hr": 3.0134,
    "ondemand_price_usd_hr": 11.877,
    "savings_pct": 74.6,
    "availability": "medium"
  },
  {
    "region": "uksouth",
    "sku": "Standard_NC48ads_A100_v4",
    "gpu_name": "A100 (80GB)",
    "gpu_count": 2,
    "vcpus": 48,
    "ram_gb": 440,
    "spot_price_usd_hr": 1.967,
    "ondemand_price_usd_hr": 9.84,
    "savings_pct": 80.0,
    "availability": "low"
  },
  {
    "region": "uksouth",
    "sku": "Standard_NC80adis_H100_v5",
    "gpu_name": "H100 (80GB)",
    "gpu_count": 2,
    "vcpus": 80,
    "ram_gb": 640,
    "spot_price_usd_hr": 12.564,
    "ondemand_price_usd_hr": 41.88,
    "savings_pct": 70.0,
    "availability": "very_low"
  },
  {
    "region": "uksouth",
    "sku": "Standard_NC12s_v3",
    "gpu_name": "Tesla V100 (16GB)",
    "gpu_count": 2,
    "vcpus": 12,
    "ram_gb": 224,
    "spot_price_usd_hr": 1.3265,
    "ondemand_price_usd_hr": 7.712,
    "savings_pct": 82.8,
    "availability": "medium"
  }
]
